athenacli/__init__.py
athenacli/athenaclirc
athenacli/clibuffer.py
athenacli/clistyle.py
athenacli/clitoolbar.py
athenacli/compat.py
athenacli/completer.py
athenacli/completion_refresher.py
athenacli/config.py
athenacli/key_bindings.py
athenacli/lexer.py
athenacli/main.py
athenacli/sqlexecute.py
athenacli/style.py
athenacli/packages/__init__.py
athenacli/packages/completion_engine.py
athenacli/packages/filepaths.py
athenacli/packages/format_utils.py
athenacli/packages/parseutils.py
athenacli/packages/prompt_utils.py
athenacli/packages/literals/__init__.py
athenacli/packages/literals/literals.json
athenacli/packages/literals/main.py
athenacli/packages/special/__init__.py
athenacli/packages/special/dbcommands.py
athenacli/packages/special/favoritequeries.py
athenacli/packages/special/iocommands.py
athenacli/packages/special/main.py
athenacli/packages/special/utils.py
athenacli/packages/tabular_output/__init__.py
athenacli/packages/tabular_output/sql_format.py
athenacli-1.6.8.dist-info/AUTHORS.rst
athenacli-1.6.8.dist-info/LICENSE.txt
athenacli-1.6.8.dist-info/METADATA
athenacli-1.6.8.dist-info/WHEEL
athenacli-1.6.8.dist-info/entry_points.txt
athenacli-1.6.8.dist-info/top_level.txt
athenacli-1.6.8.dist-info/RECORD
