Metadata-Version: 2.1
Name: athenacli
Version: 1.6.8
Summary: CLI for Athena Database. With auto-completion and syntax highlighting.
Home-page: https://github.com/dbcli/athenacli
Author: athenacli Core Team
Author-email: athenacli@googlegroups.com
License: UNKNOWN
Platform: UNKNOWN
Classifier: Intended Audience :: Developers
Classifier: License :: OSI Approved :: BSD License
Classifier: Operating System :: Unix
Classifier: Programming Language :: Python
Classifier: Programming Language :: Python :: 3
Classifier: Programming Language :: Python :: 3.6
Classifier: Programming Language :: Python :: 3.7
Classifier: Programming Language :: Python :: 3.8
Classifier: Programming Language :: SQL
Classifier: Topic :: Database
Classifier: Topic :: Database :: Front-Ends
Classifier: Topic :: Software Development
Classifier: Topic :: Software Development :: Libraries :: Python Modules
Requires-Dist: click (>=7.0)
Requires-Dist: Pygments (<=2.11.1,>=1.6)
Requires-Dist: prompt-toolkit (<4.0.0,>=3.0.3)
Requires-Dist: sqlparse (<0.5.0,>=0.3.0)
Requires-Dist: configobj (>=5.0.5)
Requires-Dist: cli-helpers[styles] (>=1.1.0)
Requires-Dist: botocore (>=1.5.52)
Requires-Dist: boto3 (>=1.4.4)
Requires-Dist: PyAthena (>=1.2.2)
